jugglerr/__init__.py
jugglerr/adapters.py
jugglerr/capabilities.py
jugglerr/cohere_adapters.py
jugglerr/embedding_adapter.py
jugglerr/exceptions.py
jugglerr/groq_adapters.py
jugglerr/jugglerr.py
jugglerr/mistral_adapters.py
jugglerr/models.py
jugglerr/models_backup.py
jugglerr/rerank_adapter.py
jugglerr/response.py
jugglerr/specialized_adapters.py
jugglerr/task_adapters.py
jugglerr/version.py
jugglerr/vision_adapters.py
jugglerr-0.2.5.dist-info/licenses/LICENSE
jugglerr-0.2.5.dist-info/METADATA
jugglerr-0.2.5.dist-info/WHEEL
jugglerr-0.2.5.dist-info/top_level.txt
jugglerr-0.2.5.dist-info/RECORD
