Metadata-Version: 2.4
Name: jugglerr
Version: 0.2.5
Summary: 🤹 Juggle multiple AI providers like a pro - Chat, embeddings, vision, and more
Author-email: Spandan Bhol <spandankb@gmail.com>
License-Expression: MIT
Project-URL: Homepage, https://github.com/spanDevOps/jugglerr
Project-URL: Documentation, https://github.com/spanDevOps/jugglerr#readme
Project-URL: Repository, https://github.com/spanDevOps/jugglerr
Project-URL: Issues, https://github.com/spanDevOps/jugglerr/issues
Keywords: ai,llm,routing,groq,cerebras,mistral,nvidia,cohere,embeddings,reranking,transcription,tts,multi-provider,anyllm,openrouter,litellm
Classifier: Development Status :: 3 - Alpha
Classifier: Intended Audience :: Developers
Classifier: Programming Language :: Python :: 3
Classifier: Programming Language :: Python :: 3.8
Classifier: Programming Language :: Python :: 3.9
Classifier: Programming Language :: Python :: 3.10
Classifier: Programming Language :: Python :: 3.11
Classifier: Programming Language :: Python :: 3.12
Requires-Python: >=3.8
License-File: LICENSE
Requires-Dist: requests>=2.31.0
Requires-Dist: tenacity>=8.2.0
Requires-Dist: python-dotenv>=0.19.0
Provides-Extra: dev
Requires-Dist: pytest>=7.4.0; extra == "dev"
Requires-Dist: pytest-cov>=4.1.0; extra == "dev"
Requires-Dist: pytest-mock>=3.11.0; extra == "dev"
Requires-Dist: responses>=0.23.0; extra == "dev"
Requires-Dist: black>=23.7.0; extra == "dev"
Requires-Dist: flake8>=6.1.0; extra == "dev"
Requires-Dist: mypy>=1.5.0; extra == "dev"
Dynamic: license-file
